vars_pickle/__Config.py
vars_pickle/__HDF5.py
vars_pickle/__init__.py
vars_pickle/__method.py
vars_pickle/__vars_manga.py
vars_pickle/__vars_pickle.py
vars_pickle-0.3.6.dist-info/LICENSE
vars_pickle-0.3.6.dist-info/METADATA
vars_pickle-0.3.6.dist-info/WHEEL
vars_pickle-0.3.6.dist-info/top_level.txt
vars_pickle-0.3.6.dist-info/RECORD
