Metadata-Version: 2.1
Name: vars-pickle
Version: 0.3.6
Summary: Save your variable as Rstudio
Home-page: https://github.com/pypa/sampleproject
Author: karond
Author-email: dingyaohui.g@outlook.com
License: UNKNOWN
Platform: UNKNOWN
Classifier: Programming Language :: Python :: 3
Classifier: License :: OSI Approved :: MIT License
Classifier: Operating System :: OS Independent
Requires-Python: >=3.6
Requires-Dist: pandas
Requires-Dist: numpy
